flask_app_security/__init__.py
flask_app_security/password_utils.py
flask_app_security/session_utils.py
flask_app_security-0.0.5.dist-info/LICENSE
flask_app_security-0.0.5.dist-info/METADATA
flask_app_security-0.0.5.dist-info/WHEEL
flask_app_security-0.0.5.dist-info/top_level.txt
flask_app_security-0.0.5.dist-info/RECORD
