Metadata-Version: 2.1
Name: flask-app-security
Version: 0.0.5
Summary: Provides utilities for securing passwords and handling user sessions.
Home-page: https://github.com/williamburriss/flask_app_security/tree/main
Author: William Burriss
Author-email: williamb03@vt.edu
License: UNKNOWN
Project-URL: Report bugs, https://github.com/williamburriss/flask_app_security/issues
Platform: UNKNOWN
Classifier: Programming Language :: Python :: 3
Classifier: License :: OSI Approved :: MIT License
Classifier: Operating System :: OS Independent
Requires-Python: >=3.6
License-File: LICENSE
Requires-Dist: joserfc >=0.7.0
